README.md
setup.py
valpy/__init__.py
valpy.egg-info/PKG-INFO
valpy.egg-info/SOURCES.txt
valpy.egg-info/dependency_links.txt
valpy.egg-info/requires.txt
valpy.egg-info/top_level.txt
valpy/backtest/__init__.py
valpy/backtest/backtest.py
valpy/backtest/interesting_periods.py
valpy/backtest/plotting.py
valpy/backtest/pyfolio.py
valpy/backtest/report.py
valpy/data/__init__.py
valpy/data/equity.py
valpy/data/options.py