Metadata-Version: 1.1
Name: valpy
Version: 0.0.1
Summary: A python client for finance related jobs
Home-page: UNKNOWN
Author: Yiheng Li
Author-email: UNKNOWN
License: UNKNOWN
Platform: any
Classifier: Programming Language :: Python :: 3
